[{"id":"ST16-001","setCode":"ST16","number":"001","name":"Uta","type":"Character","color":["Green"],"rarity":"SR","cost":4,"power":6000,"counter":null,"life":null,"traits":[],"effect":"[Blocker] (After your opponent declares an attack, you may rest this card to make it the new target of the attack.) [Activate: Main] [Once Per Turn] You may trash 1","isBlocker":true,"imageUrl":"https://limitlesstcg.nyc3.cdn.digitaloceanspaces.com/one-piece/ST16/ST16-001_EN.webp","isDemo":true},{"id":"ST16-002","setCode":"ST16","number":"002","name":"Gordon","type":"Character","color":["Green"],"rarity":"C","cost":2,"power":0,"counter":1000,"life":null,"traits":[],"effect":"[Blocker] (After your opponent declares an attack, you may rest this card to make it the new target of the attack.) [On Your Opponent's Attack] You may trash any number of type cards from your hand. Your Leader or 1 of your Characters gains +1000 power during this battle for every card trashed.","isBlocker":true,"imageUrl":"https://limitlesstcg.nyc3.cdn.digitaloceanspaces.com/one-piece/ST16/ST16-002_EN.webp","isDemo":true},{"id":"ST16-003","setCode":"ST16","number":"003","name":"Charlotte Katakuri","type":"Character","color":["Green"],"rarity":"C","cost":3,"power":4000,"counter":1000,"life":null,"traits":["FILM","Big Mom Pirates"],"effect":"type and you have 6 or more rested cards, this Character gains +2000 power.","imageUrl":"https://limitlesstcg.nyc3.cdn.digitaloceanspaces.com/one-piece/ST16/ST16-003_EN.webp","isDemo":true},{"id":"ST16-004","setCode":"ST16","number":"004","name":"Shanks","type":"Character","color":["Green"],"rarity":"SR","cost":9,"power":11000,"counter":null,"life":null,"traits":["FILM","The Four Emperors","Red-Haired Pirates"],"effect":"[On Play] K.O. up to 1 of your opponent's rested Characters.","imageUrl":"https://limitlesstcg.nyc3.cdn.digitaloceanspaces.com/one-piece/ST16/ST16-004_EN.webp","isDemo":true},{"id":"ST16-005","setCode":"ST16","number":"005","name":"Monkey.D.Luffy","type":"Character","color":["Green"],"rarity":"C","cost":2,"power":3000,"counter":2000,"life":null,"traits":["FILM","Supernovas","Straw Hat Crew"],"effect":"If you have a rested [Uta], this Character gains +1000 power.","imageUrl":"https://limitlesstcg.nyc3.cdn.digitaloceanspaces.com/one-piece/ST16/ST16-005_EN.webp","isDemo":true}]